{
    "preload" : false,
    "resources" : {
        "dict" : [
                { 
                    "name" : "debug_vars",
                    "dict" : {
                                "fw_seek" : 20.0,
                                "eaos_saver_finalized" : true
                    }
                },
                {
                    "name" : "landing_enviro_config",
                    "dict" : {
                        "room_range" : { "left" : -42.0, "right" : 42.0 } 
                    }
                },
                {
                    "name" : "player_config",
                    "dict" : {
                        "walk" : {
                            "speed" : 0.06,
                            "smoothing" : 0.01,
                            "decay" : 0.94
                        }
                    }
                }
            ],
        "shader" : [
        {
            "name"              : "terminal",
            "vertex_program"    : "2d_transform",
            "pixel_program"     : "postfx/station/terminal"
        } ],
        "texture" : [
            {   
                "name" : "bgplanet",
                "filename" : "sprite/png/sylabhead.png",
                "filtered" : false
            },
            {   
                "name" : "infra_overview",
                "filename" : "sprite/png/infra_sketch_2.png",
                "filtered" : false
            },
            {   
                "name" : "termlay",
                "filename" : "sprite/png/termlay.png",
                "filtered" : false
            },
            {   
                "name" : "ident",
                "filename" : "sprite/png/infra_sketch_3.png",
                "filtered" : false
            },
            {   
                "name" : "crsr",
                "filename" : "sprite/png/crsr.png",
                "filtered" : false
            },
        {   
            "name" : "sylab_phase_0_head",
            "filename" : "sprite/png/sylabhead.png",
            "filtered" : false
        },
        {   
            "name" : "posters/binary",
            "filename" : "sprite/png/poster_binary.png",
            "filtered" : false
        },
        {   
            "name" : "posters/inactive",
            "filename" : "sprite/png/poster_inactive.png",
            "filtered" : false
        },
        {   
            "name" : "posters/unity",
            "filename" : "sprite/png/poster_unity.png",
            "filtered" : false
        }
        ],
            "curve_sequence" : [
            {
                "name" : "disp_warp",
                "sequence" : {
                    "loop" : false,
                    "timescale" : 0.7,
                    "start"     : 0.0,
                    "end"       : 10.0,
                    "scenes" : {
                        "disp_warp" : { "start" : 0.0, "end" : 10.0 }
                    },
                    "curves" : {
                        "disp_warp" : {
                            "terminal_scale" : [
                                    { "t" : 2.0, "vec" : [ 20.0,20.0] },
                                    { "t" : 6.0, "vec" : [ 4.0,4.0 ], "smooth" : "invsqr" }  
                                ],
                            "warp" : [
                            { "t" : 2.0, "vec" : [ 1.0 ] },
                            { "t" : 4.9, "vec" : [ 0.0 ], "smooth" : "sqr" }
                            ],
                                "filter_color" : [
                                { "t" : 4.0, "vec" : [ 0.0,0.0,0.0,0.0 ] },
                                { "t" : 4.2, "vec" : [ 0.0,0.0,1.0,0.5 ] },
                                { "t" : 4.8, "vec" : [ 0.0,1.0,1.0,0.6 ] },
                                { "t" : 4.9, "vec" : [ 1.0,0.0,0.0,0.2 ] },
                                { "t" : 5.3, "vec" : [ 0.9,1.0,1.0,0.3 ] },
                                { "t" : 6.0, "vec" : [ 1.0,1.0,1.0,1.0] , "smooth" : "sqr" },
                                { "t" : 9.0, "vec" : [ 0.7,0.9,1.0,1.0] , "smooth" : "invsqr" }
                            ]
                        }
                    }
                }
            }]
    }
}
